rca/__init__.py
rca/__main__.py
rca/rca.py
rca/track.py
rca/config/aac-profiles.yml
rca/config/flac-profiles.yml
rca/config/he-aac-profiles.yml
rca/config/he-aac-v2-profiles.yml
rca/config/master_properties.yml
rca/config/mp3-profiles.yml
rca/config/opus-profiles.yml
rca/config/properties.yml
rca/config/vorbis-profiles.yml
rca/test/properties.yml
rca/test/track02.wav
rca/test/track03.wav
rca/test/track04.wav
rca/test/track05.wav
rca/test/track06.wav
rca/test/track07.wav
rca/test/track08.wav
rca/test/track09.wav
rca/test/track10.wav
rca/test/track11.wav
rca/test/track12.wav
rca-0.8.2.dist-info/LICENSE
rca-0.8.2.dist-info/METADATA
rca-0.8.2.dist-info/WHEEL
rca-0.8.2.dist-info/entry_points.txt
rca-0.8.2.dist-info/top_level.txt
rca-0.8.2.dist-info/RECORD
