Metadata-Version: 2.1
Name: rca
Version: 0.8.2
Summary: Recompress Audio
Home-page: https://gitlab.com/krcroft/rca
Author: Kevin R Croft
Author-email: krcroft@gmail.com
License: UNKNOWN
Keywords: audio encoding vorbis ogg opus mp3 aac music speech mono stereo
Platform: UNKNOWN
Classifier: Development Status :: 4 - Beta
Classifier: Intended Audience :: End Users/Desktop
Classifier: License :: OSI Approved :: GNU General Public License v3 or later (GPLv3+)
Classifier: Operating System :: OS Independent
Classifier: Programming Language :: Python :: 3 :: Only
Classifier: Programming Language :: Python :: 3.5
Classifier: Programming Language :: Python :: 3.6
Classifier: Programming Language :: Python :: 3.7
Classifier: Programming Language :: Python :: Implementation :: CPython
Classifier: Topic :: Multimedia :: Sound/Audio :: Conversion
Classifier: Topic :: Utilities
Requires-Python: >=3.5
Requires-Dist: appdirs
Requires-Dist: attrs
Requires-Dist: colorlog
Requires-Dist: yaml
